django_rest_form_fields/__init__.py
django_rest_form_fields/compatibility.py
django_rest_form_fields/exceptions.py
django_rest_form_fields/fields.py
django_rest_form_fields/forms.py
django_rest_form_fields/validators.py
django_rest_form_fields-1.4.2.dist-info/licenses/LICENSE
django_rest_form_fields-1.4.2.dist-info/METADATA
django_rest_form_fields-1.4.2.dist-info/WHEEL
django_rest_form_fields-1.4.2.dist-info/top_level.txt
django_rest_form_fields-1.4.2.dist-info/RECORD
