Metadata-Version: 2.4
Name: django-rest-form-fields
Version: 1.4.2
Summary: Extended form fields to validate REST-request data via django.forms
Home-page: https://github.com/M1hacka/django-rest-form-fields
Author: Mikhail Shvein
Author-email: work_shvein_mihail@mail.ru
License: BSD 3-clause "New" or "Revised" License
License-File: LICENSE
Requires-Dist: django>=1.7
Requires-Dist: typing; python_version < "3.5"
Dynamic: author
Dynamic: author-email
Dynamic: description
Dynamic: description-content-type
Dynamic: home-page
Dynamic: license
Dynamic: license-file
Dynamic: requires-dist
Dynamic: summary
